matplotlib_pyodide/__init__.py
matplotlib_pyodide/browser_backend.py
matplotlib_pyodide/html5_canvas_backend.py
matplotlib_pyodide/wasm_backend.py
matplotlib_pyodide-0.2.1.dist-info/LICENSE
matplotlib_pyodide-0.2.1.dist-info/METADATA
matplotlib_pyodide-0.2.1.dist-info/WHEEL
matplotlib_pyodide-0.2.1.dist-info/top_level.txt
matplotlib_pyodide-0.2.1.dist-info/RECORD
