Metadata-Version: 2.1
Name: matplotlib-pyodide
Version: 0.2.1
Summary: HTML5 backends for Matplotlib compatible with Pyodide
Author: Pyodide developers
License: Mozilla Public License Version 2.0
Project-URL: Homepage, https://github.com/pyodide/matplotlib-pyodide
Project-URL: Bug Tracker, https://github.com/pyodide/matplotlib-pyodide/issues
Classifier: Programming Language :: Python :: 3
Classifier: License :: OSI Approved :: Mozilla Public License 2.0 (MPL 2.0)
Classifier: Operating System :: OS Independent
Requires-Python: >=3.10
License-File: LICENSE
Provides-Extra: test
Requires-Dist: pytest-pyodide==0.52.2; extra == "test"
Requires-Dist: pytest-cov; extra == "test"
Requires-Dist: build==0.10; extra == "test"
